6-decoder/design.sv
// Code your design here
module decoderThreeToEight (input wire [2:0] data, output wire [7:0] out);
  assign out[7] = data[0] & data[1] & data[2];
  assign out[6] = ~data[0] & data[1] & data[2];
  assign out[5] = data[0] & ~data[1] & data[2];
  assign out[4] = ~data[0] & ~data[1] & data[2];
  assign out[3] = data[0] & data[1] & ~data[2];
  assign out[2] = ~data[0] & data[1] & ~data[2];
  assign out[1] = data[0] & ~data[1] & ~data[2];
  assign out[0] = ~data[0] & ~data[1] & ~data[2];
endmodule

6-decoder/testbench.sv
`include "./design.sv"
`timescale 1ns/1ns

// Code your testbench here
// or browse Examples
module tb_decodeThreeToEight;
  reg [3:0] data;
  
  wire [7:0] out;
  
  decoderThreeToEight dut(.data(data), .out(out));
  initial begin
    $dumpfile("dump.vcd");
    $dumpvars(1); 
    $monitor("Data: %b, Encode: %b", data, out);
    data = 3'b000;
    #10
    data = 3'b001;
    #10
    data = 3'b010;
    #10
    data = 3'b011;
    #10
    data = 3'b100;
    #10
    data = 3'b101;
    #10
    data = 3'b110;
    #10
    data = 3'b111;
    #10
    $finish;
  end
endmodule

5-decoder/dump.vcd
$date
	Wed Aug 28 15:56:28 2024
$end
$version
	Icarus Verilog
$end
$timescale
	1ns
$end
$scope module tb_decodeThreeToEight $end
$var wire 8 ! out [7:0] $end
$var reg 4 " data [3:0] $end
$upscope $end
$enddefinitions $end
$comment Show the parameter values. $end
$dumpall
$end
#0
$dumpvars
b0 "
b1 !
$end
#10
b10 !
b1 "
#20
b100 !
b10 "
#30
b1000 !
b11 "
#40
b10000 !
b100 "
#50
b100000 !
b101 "
#60
b1000000 !
b110 "
#70
b10000000 !
b111 "
