7-digitdisplay/design.sv
// Code your design here
// Code your design here
module bcdToSeven (input wire [3:0] data, output wire a,b,c,d,e,f,g);
  assign a = data[3] | data[2] & data[0] | data[1] | ~data[2] & ~data[0];
  assign b = ~data[2] | ~data[1] & ~data[0] | data[1] & data[0];
  assign c = ~data[1] | data[0] | data[2];
  assign d = ~data[2] & ~data[0] | ~data[2] & data[1] | data[2] & ~data[1] & data[0] | data[1] & ~data[0] | data[3];
  assign e = ~data[2] & ~data[0] | data[1] & ~data[0];
  assign f = ~data[1] & ~data[0] | data[2] & ~data[1] | data[2] & ~data[0] | data[3];
  assign g = ~data[2] & data[1] | data[2] & ~data[1] | data[3] | data[2] & ~data[0];
endmodule

6-digitdisplay/testbench.sv
`include "./design.sv"
`timescale 1ns/1ns

// Code your testbench here
// or browse Examples
module tb_bcdToSeven;
  reg [3:0] data;
  
  wire a;
  wire b;
  wire c;
  wire d;
  wire e;
  wire f;
  wire g;
  
  bcdToSeven dut (.data(data), .a(a), .b(b), .c(c), .d(d), .e(e), .f(f), .g(g));
  initial begin
    $dumpfile("dump.vcd");
    $dumpvars(1); 
    $monitor("Data: %b, a: %b, b: %b, c: %b, d: %b, e: %b, f: %b, g: %b", data, a,b,c,d,e,f,g);
    data = 4'b0000;
    #10
    data = 4'b0001;
    #10
    data = 4'b0010;
    #10
    data = 4'b0011;
    #10
    data = 4'b0100;
    #10
    data = 4'b0101;
    #10
    data = 4'b0110;
    #10
    data = 4'b0111;
    #10
    data = 4'b1000;
    #10
    data = 4'b1001;
    #10
    $finish;
  end
endmodule

6-digitdisplay/dump.vcd
$date
	Wed Aug 28 16:05:25 2024
$end
$version
	Icarus Verilog
$end
$timescale
	1ns
$end
$scope module tb_bcdToSeven $end
$var wire 1 ! g $end
$var wire 1 " f $end
$var wire 1 # e $end
$var wire 1 $ d $end
$var wire 1 % c $end
$var wire 1 & b $end
$var wire 1 ' a $end
$var reg 4 ( data [3:0] $end
$upscope $end
$enddefinitions $end
$comment Show the parameter values. $end
$dumpall
$end
#0
$dumpvars
b0 (
1'
1&
1%
1$
1#
1"
0!
$end
#10
0$
0"
0'
0#
b1 (
#20
1!
0%
1$
1'
1#
b10 (
#30
0#
1%
b11 (
#40
0$
1"
0'
b100 (
#50
1'
0&
1$
b101 (
#60
1#
b110 (
#70
0$
0"
0#
0!
1&
b111 (
#80
1#
1&
1%
1!
1$
1"
b1000 (
#90
0#
b1001 (
