5-encoder/design.sv
// Code your design here
module encoderEightToThree (input wire [7:0] data, output wire [2:0] out);
  assign out[2] = data[4] + data[5] + data[6] + data[7];
  assign out[1] = data[2] + data[3] + data[6] + data[7];
  assign out[0] = data[1] + data[3] + data[5] + data[7];
endmodule

5-encoder/testbench.sv
`include "./design.sv"
`timescale 1ns/1ns

// Code your testbench here
// or browse Examples
module tb_encodeEightToThree;
  reg [7:0] data;
  
  wire [2:0] out;
  
  encoderEightToThree dut(.data(data), .out(out));
  initial begin
    $dumpfile("dump.vcd");
    $dumpvars(1); 
    $monitor("Data: %b, Encode: %b", data, out);
    data = 8'b0000_0000;
    #10
    data = 8'b0000_0010;
    #10
    data = 8'b0000_0100;
    #10
    data = 8'b0000_1000;
    #10
    data = 8'b0001_0000;
    #10
    data = 8'b0010_0000;
    #10
    data = 8'b0100_0000;
    #10
    data = 8'b1000_0000;
    #10
    $finish;
  end
endmodule

4-encoder/dump.vcd
$date
	Wed Aug 28 15:49:10 2024
$end
$version
	Icarus Verilog
$end
$timescale
	1ns
$end
$scope module tb_encodeEightToThree $end
$var wire 3 ! out [2:0] $end
$var reg 8 " data [7:0] $end
$upscope $end
$enddefinitions $end
$comment Show the parameter values. $end
$dumpall
$end
#0
$dumpvars
b0 "
b0 !
$end
#10
b1 !
b10 "
#20
b10 !
b100 "
#30
b11 !
b1000 "
#40
b100 !
b10000 "
#50
b101 !
b100000 "
#60
b110 !
b1000000 "
#70
b111 !
b10000000 "
