3-mux/design.sv
// Code your design here
module sixteenToOne (input wire [15:0] data, input wire [3:0] selector, output reg out);
  always @* begin
    case (selector)
      4'b0000: 
        out = data[0];
      4'b0001: 
        out = data[1];
      4'b0010:
        out = data[2];
      4'b0011:
        out = data[3];
      4'b0100:
        out = data[4];
      4'b0101:
        out = data[5];
      4'b0110:
        out = data[6];
      4'b0111:
        out = data[7];
      4'b1000:
        out = data[8];
      4'b1001:
        out = data[9];
      4'b1010:
        out = data[10];
      4'b1011:
        out = data[11];
      4'b1100:
        out = data[12];
      4'b1101:
        out = data[13];
      4'b1110:
        out = data[14];
      4'b1111:
        out = data[15];
      default: out = 16'b0; // Default case (optional).
    endcase
  end
endmodule

3-mux/testbench.sv
`include "./design.sv"
`timescale 1ns/1ns

module tb_sixteenToOne;
  // Inputs
  reg [15:0] data;
  reg [3:0] selector;
  // Outputs
  wire out;
  // Instantiate the module under test
  sixteenToOne dut (
    .data(data),
    .selector(selector),
    .out(out)
  );
  // Stimulus
  initial begin
    $dumpfile("dump.vcd");
    $dumpvars(1); 
    $monitor("Selector: %b, Data: %b, Output: %b", selector, data, out);
    selector = 4'b0000;
    data = 16'b0000_0000_0000_0001;
    #10
    selector = 4'b0001;
    data = 16'b0000_0000_0000_0010;
    #10
    selector = 4'b0010;
    data = 16'b0000_0000_0000_0100;
    #10
    selector = 4'b0011;
    data = 16'b0000_0000_0000_1000;
    #10
    selector = 4'b0100;
    data = 16'b0000_0000_0001_0000;
    #10
    selector = 4'b0101;
    data = 16'b0000_0000_0010_0000;
    #10
    selector = 4'b0110;
    data = 16'b0000_0000_0100_0000;
    #10
    selector = 4'b0111;
    data = 16'b0000_0000_1000_0000;
    #10
    selector = 4'b1000;
    data = 16'b0000_0001_0000_0000;
    #10
    selector = 4'b1001;
    data = 16'b0000_0010_0000_0000;
    #10
    selector = 4'b1010;
    data = 16'b0000_0100_0000_0000;
    #10
    selector = 4'b1011;
    data = 16'b0000_1000_0000_0000;
    #10
    selector = 4'b1100;
    data = 16'b0001_0000_0000_0000;
    #10
    selector = 4'b1101;
    data = 16'b0010_0000_0000_0000;
    #10
    selector = 4'b1110;
    data = 16'b0100_0000_0000_0000;
    #10
    selector = 4'b1111;
    data = 16'b1000_0000_0000_0000;
    #10
    $finish;
  end
endmodule

3-mux/dump.vcd
$date
	Wed Aug 28 15:45:28 2024
$end
$version
	Icarus Verilog
$end
$timescale
	1ns
$end
$scope module tb_sixteenToOne $end
$var wire 1 ! out $end
$var reg 16 " data [15:0] $end
$var reg 4 # selector [3:0] $end
$upscope $end
$enddefinitions $end
$comment Show the parameter values. $end
$dumpall
$end
#0
$dumpvars
b0 #
b1 "
1!
$end
#10
b10 "
b1 #
#20
b100 "
b10 #
#30
b1000 "
b11 #
#40
b10000 "
b100 #
#50
b100000 "
b101 #
#60
b1000000 "
b110 #
#70
b10000000 "
b111 #
#80
b100000000 "
b1000 #
#90
b1000000000 "
b1001 #
#100
b10000000000 "
b1010 #
#110
b100000000000 "
b1011 #
#120
b1000000000000 "
b1100 #
#130
b10000000000000 "
b1101 #
#140
b100000000000000 "
b1110 #
#150
b1000000000000000 "
b1111 #
